AIAgent/Agent/__init__.py
AIAgent/Agent/agent.py
AIAgent/Agent/plugin_manager.py
robotframework_aiagent_slim-0.0.1.dist-info/METADATA
robotframework_aiagent_slim-0.0.1.dist-info/WHEEL
robotframework_aiagent_slim-0.0.1.dist-info/RECORD
