Metadata-Version: 2.4
Name: robotframework-aiagent-slim
Version: 0.0.1
Summary: Robot Framework AI Agent core library
License: Apache-2.0
Requires-Python: >=3.10
Requires-Dist: pydantic-ai-slim>=1.0.0
Requires-Dist: robotframework>=7.0
Requires-Dist: typing-extensions>=4.14.0
Provides-Extra: anthropic
Requires-Dist: pydantic-ai-slim[anthropic]; extra == 'anthropic'
Provides-Extra: bedrock
Requires-Dist: pydantic-ai-slim[bedrock]; extra == 'bedrock'
Provides-Extra: cohere
Requires-Dist: pydantic-ai-slim[cohere]; extra == 'cohere'
Provides-Extra: duckduckgo
Requires-Dist: pydantic-ai-slim[duckduckgo]; extra == 'duckduckgo'
Provides-Extra: google
Requires-Dist: pydantic-ai-slim[google]; extra == 'google'
Provides-Extra: groq
Requires-Dist: pydantic-ai-slim[groq]; extra == 'groq'
Provides-Extra: huggingface
Requires-Dist: pydantic-ai-slim[huggingface]; extra == 'huggingface'
Provides-Extra: mcp
Requires-Dist: pydantic-ai-slim[mcp]; extra == 'mcp'
Provides-Extra: mistral
Requires-Dist: pydantic-ai-slim[mistral]; extra == 'mistral'
Provides-Extra: openai
Requires-Dist: pydantic-ai-slim[openai]; extra == 'openai'
Provides-Extra: vertexai
Requires-Dist: pydantic-ai-slim[vertexai]; extra == 'vertexai'
